LICENSE.txt
MANIFEST.in
README.rst
requirements.txt
setup.py
bgsignature/__init__.py
bgsignature/cli.py
bgsignature/error.py
bgsignature/file.py
bgsignature/load.py
bgsignature/main.py
bgsignature/reference.py
bgsignature/utils.py
bgsignature.egg-info/PKG-INFO
bgsignature.egg-info/SOURCES.txt
bgsignature.egg-info/dependency_links.txt
bgsignature.egg-info/entry_points.txt
bgsignature.egg-info/requires.txt
bgsignature.egg-info/top_level.txt
bgsignature/count/__init__.py
bgsignature/count/mutation.py
bgsignature/count/region.py
bgsignature/count/utils.py
test/__init__.py
test/reference.py
test/test_count_mutations.py
test/test_count_regions.py
test/test_frequency.py
test/test_normalization.py
test/test_parallel.py