Metadata-Version: 2.1
Name: bgsignature
Version: 0.2
Summary: Compute genome signatures
Home-page: https://bitbucket.org/bgframework/bgsignature
Author: Barcelona Biomedical Genomics Lab
Author-email: bbglab@irbbarcelona.org
License: Apache Software License 2.0
Platform: UNKNOWN
